mycalc/calculator.py
gyk230411-1.0.1.dist-info/METADATA
gyk230411-1.0.1.dist-info/WHEEL
gyk230411-1.0.1.dist-info/top_level.txt
gyk230411-1.0.1.dist-info/RECORD
