Metadata-Version: 2.1
Name: gyk230411
Version: 1.0.1
Summary: nice calc
Home-page: https://github.com/Geun|yeong-Kwon/OSS-Development.git
Download-URL: https://github.com/Geunyeong-Kwon/oss/releases/tag/v0.0.1
Author: gy0
License: UNKNOWN
Platform: UNKNOWN
Classifier: Programming Language :: Python :: 3
